llama_slobber/__init__.py
llama_slobber/act_on_all_rundles.py
llama_slobber/calc_hun.py
llama_slobber/calc_wonder.py
llama_slobber/comp_hun.py
llama_slobber/find_stored_stat.py
llama_slobber/find_wlt_patterns.py
llama_slobber/fmt_float.py
llama_slobber/fmt_html_calc.py
llama_slobber/get_dir_with_field.py
llama_slobber/handle_conn_err.py
llama_slobber/ll_collect_onedays.py
llama_slobber/ll_get_rundle_comp.py
llama_slobber/ll_leagues.py
llama_slobber/ll_local_io.py
llama_slobber/ll_matchcount.py
llama_slobber/ll_matchday.py
llama_slobber/ll_matchresult.py
llama_slobber/ll_oneday_players.py
llama_slobber/ll_onedays.py
llama_slobber/ll_parse_oneday_get_date.py
llama_slobber/ll_personal_data.py
llama_slobber/ll_qhist.py
llama_slobber/ll_read_csv_file.py
llama_slobber/ll_rundle_members.py
llama_slobber/ll_rundles.py
llama_slobber/ll_season.py
llama_slobber/ll_user_record.py
llama_slobber/lookup_user.py
llama_slobber/out_csv_file.py
llama_slobber/stringify.py
llama_slobber-1.0.27.dist-info/LICENSE
llama_slobber-1.0.27.dist-info/METADATA
llama_slobber-1.0.27.dist-info/WHEEL
llama_slobber-1.0.27.dist-info/top_level.txt
llama_slobber-1.0.27.dist-info/RECORD
