Metadata-Version: 2.1
Name: llama-slobber
Version: 1.0.27
Summary: Slobr utilities
Home-page: https://github.com/pypa/sampleproject
Author: Warren Usui
Author-email: warrenusui@gmail.com
License: UNKNOWN
Platform: UNKNOWN
Classifier: Programming Language :: Python :: 3
Classifier: License :: OSI Approved :: MIT License
Classifier: Operating System :: OS Independent
